{
  "platform": "Instagram",
  "url": "https://www.instagram.com/93_stalin/",
  "extraction": {
    "visible_name": "93_stalin",
    "username": "93_stalin",
    "url": "https://www.instagram.com/93_stalin/",
    "timestamp": "2026-04-09T20:32:20.906971",
    "confidence": 1.0,
    "selector_used": "Multi-selector approach"
  },
  "steps": [
    {
      "name": "Browser Start",
      "status": "PASS",
      "message": "Chrome connected",
      "screenshot_path": null,
      "timestamp": "2026-04-09T20:32:17.919380"
    },
    {
      "name": "Navigation",
      "status": "PASS",
      "message": "Arrived at https://www.instagram.com/93_stalin/",
      "screenshot_path": null,
      "timestamp": "2026-04-09T20:32:20.190473"
    },
    {
      "name": "Extraction",
      "status": "PASS",
      "message": "Visible name: 93_stalin",
      "screenshot_path": null,
      "timestamp": "2026-04-09T20:32:20.906971"
    },
    {
      "name": "Follow Action",
      "status": "PASS",
      "message": "User followed (or already following)",
      "screenshot_path": null,
      "timestamp": "2026-04-09T20:32:21.013992"
    },
    {
      "name": "Message Builder",
      "status": "PASS",
      "message": "Official professional draft ready",
      "screenshot_path": null,
      "timestamp": "2026-04-09T20:32:21.013992"
    },
    {
      "name": "Chat Transition",
      "status": "PASS",
      "message": "Opened DM window",
      "screenshot_path": null,
      "timestamp": "2026-04-09T20:32:26.481239"
    },
    {
      "name": "Interaction Probe",
      "status": "FAIL",
      "message": "Message textbox not found",
      "screenshot_path": null,
      "timestamp": "2026-04-09T20:32:26.556641"
    }
  ],
  "summary": "Full automated invitation cycle completed."
}